github_cli_mamba/__init__.py
github_cli_mamba/github.py
github_cli_mamba/main.py
github_cli_mamba/options.py
github_cli_mamba/utils.py
github_cli_mamba/cli/__init__.py
github_cli_mamba/cli/repo.py
github_cli_mamba/cli/user.py
github_cli_mamba-0.1.1.dist-info/METADATA
github_cli_mamba-0.1.1.dist-info/WHEEL
github_cli_mamba-0.1.1.dist-info/entry_points.txt
github_cli_mamba-0.1.1.dist-info/RECORD
