Metadata-Version: 2.4
Name: github-cli-mamba
Version: 0.1.1
Summary: A GitHub CLI tool built with Python and Typer
Author-email: lishaojie <shaojieli.nlp@gmail.com>
Requires-Python: >=3.10
Requires-Dist: jmespath>=1.0.1
Requires-Dist: python-dotenv>=1.0.1
Requires-Dist: requests>=2.32.3
Requires-Dist: typer[all]>=0.15.2
